dpgen/.gitignore
dpgen/__init__.py
dpgen/_version.py
dpgen/arginfo.py
dpgen/gui.py
dpgen/main.py
dpgen/util.py
dpgen/auto_test/ABACUS.py
dpgen/auto_test/EOS.py
dpgen/auto_test/Elastic.py
dpgen/auto_test/Gamma.py
dpgen/auto_test/Interstitial.py
dpgen/auto_test/Lammps.py
dpgen/auto_test/Property.py
dpgen/auto_test/Surface.py
dpgen/auto_test/Task.py
dpgen/auto_test/VASP.py
dpgen/auto_test/Vacancy.py
dpgen/auto_test/__init__.py
dpgen/auto_test/calculator.py
dpgen/auto_test/common_equi.py
dpgen/auto_test/common_prop.py
dpgen/auto_test/gen_confs.py
dpgen/auto_test/mpdb.py
dpgen/auto_test/refine.py
dpgen/auto_test/reproduce.py
dpgen/auto_test/run.py
dpgen/auto_test/lib/__init__.py
dpgen/auto_test/lib/abacus.py
dpgen/auto_test/lib/crys.py
dpgen/auto_test/lib/lammps.py
dpgen/auto_test/lib/lmp.py
dpgen/auto_test/lib/mfp_eosfit.py
dpgen/auto_test/lib/pwscf.py
dpgen/auto_test/lib/siesta.py
dpgen/auto_test/lib/util.py
dpgen/auto_test/lib/utils.py
dpgen/auto_test/lib/vasp.py
dpgen/auto_test/template/elastic/lmp/displace.mod
dpgen/auto_test/template/elastic/lmp/in.elastic
dpgen/auto_test/template/elastic/lmp/init.mod
dpgen/auto_test/template/elastic/lmp/potential.mod
dpgen/auto_test/template/incars/INCAR.relax
dpgen/auto_test/template/incars/INCAR.static
dpgen/collect/__init__.py
dpgen/collect/collect.py
dpgen/data/__init__.py
dpgen/data/arginfo.py
dpgen/data/gen.py
dpgen/data/reaction.py
dpgen/data/surf.py
dpgen/data/jsons/al.diamond.111.json
dpgen/data/jsons/al.diamond.222.json
dpgen/data/jsons/al.fcc.111.json
dpgen/data/jsons/al.fcc.222.json
dpgen/data/jsons/al.hcp.111.json
dpgen/data/jsons/al.hcp.222.json
dpgen/data/jsons/al.hcp.332.json
dpgen/data/jsons/al.sc.222.json
dpgen/data/jsons/almg.diamond.111.json
dpgen/data/jsons/almg.diamond.222.json
dpgen/data/jsons/almg.fcc.111.json
dpgen/data/jsons/almg.fcc.222.json
dpgen/data/jsons/almg.hcp.111.json
dpgen/data/jsons/almg.hcp.222.json
dpgen/data/jsons/almg.hcp.332.json
dpgen/data/jsons/almg.sc.222.json
dpgen-0.13.2.dist-info/licenses/LICENSE
dpgen-0.13.2.dist-info/METADATA
dpgen-0.13.2.dist-info/WHEEL
dpgen-0.13.2.dist-info/entry_points.txt
dpgen-0.13.2.dist-info/top_level.txt
dpgen-0.13.2.dist-info/RECORD
