Metadata-Version: 2.4
Name: dpgen
Version: 0.13.2
Summary: DP-GEN: The deep potential generator
Author: DeepModeling
Author-email: Han Wang <wang_han@iapcm.ac.cn>
License:                    GNU LESSER GENERAL PUBLIC LICENSE
Project-URL: Homepage, https://github.com/deepmodeling/dpgen
Project-URL: documentation, https://docs.deepmodeling.com/projects/dpgen
Project-URL: repository, https://github.com/deepmodeling/dpgen
Keywords: deep potential generator,active learning,deepmd-kit
Classifier: Programming Language :: Python :: 3.9
Classifier: Programming Language :: Python :: 3.10
Classifier: Programming Language :: Python :: 3.11
Classifier: License :: OSI Approved :: GNU Lesser General Public License v3 (LGPLv3)
Requires-Python: >=3.9
License-File: LICENSE
Requires-Dist: numpy>=1.14.3
Requires-Dist: dpdata>=0.2.23
Requires-Dist: cp2kdata>=0.6.6
Requires-Dist: pymatgen>=2022.11.1
Requires-Dist: ase
Requires-Dist: monty>2.0.0
Requires-Dist: paramiko
Requires-Dist: custodian
Requires-Dist: GromacsWrapper>=0.8.0
Requires-Dist: GromacsWrapper>=0.9.0; python_version >= "3.12"
Requires-Dist: dpdispatcher>=0.3.11
Requires-Dist: netCDF4
Requires-Dist: dargs>=0.4.0
Requires-Dist: h5py
Requires-Dist: pymatgen-analysis-defects
Requires-Dist: openbabel-wheel
Requires-Dist: packaging
Provides-Extra: test
Requires-Dist: dpgui; extra == "test"
Requires-Dist: coverage; extra == "test"
Requires-Dist: pymatgen-analysis-defects>=2024.10.22; python_version >= "3.10" and extra == "test"
Provides-Extra: gui
Requires-Dist: dpgui; extra == "gui"
Dynamic: license-file
